fbfeed/__init__.py
fbfeed/admin.py
fbfeed/apps.py
fbfeed/defaults.py
fbfeed/models.py
fbfeed/migrations/0001_initial.py
fbfeed/migrations/__init__.py
fbfeed/templates/admin/fbfeed/access/change_form.html
fbfeed/templatetags/__init__.py
fbfeed/templatetags/fbfeed_tags.py
mezzanine_facebook_feed-0.3.1.dist-info/LICENSE
mezzanine_facebook_feed-0.3.1.dist-info/METADATA
mezzanine_facebook_feed-0.3.1.dist-info/WHEEL
mezzanine_facebook_feed-0.3.1.dist-info/top_level.txt
mezzanine_facebook_feed-0.3.1.dist-info/RECORD
