Metadata-Version: 2.1
Name: mezzanine-facebook-feed
Version: 0.3.1
Summary: Connect Mezzanine sites to Facebook feeds
Home-page: https://github.com/unplugstudio/mezzanine-facebook-feed
Author: Unplug Studio
Author-email: hello@unplug.studio
License: MIT
Keywords: django mezzanine facebook
Platform: UNKNOWN
Classifier: Development Status :: 5 - Production/Stable
Classifier: Intended Audience :: Developers
Classifier: Topic :: Software Development :: Libraries
Classifier: License :: OSI Approved :: MIT License
Classifier: Programming Language :: Python :: 2
Classifier: Programming Language :: Python :: 2.7
Classifier: Programming Language :: Python :: 3
Classifier: Programming Language :: Python :: 3.6
Classifier: Programming Language :: Python :: 3.7
Classifier: Programming Language :: Python :: 3.8
Requires-Dist: mezzanine (>=4.3.0)
